LICENSE
MANIFEST.in
setup.py
pyopenapi/VERSION
pyopenapi/__init__.py
pyopenapi/consts.py
pyopenapi/errs.py
pyopenapi/utils.py
pyopenapi.egg-info/PKG-INFO
pyopenapi.egg-info/SOURCES.txt
pyopenapi.egg-info/dependency_links.txt
pyopenapi.egg-info/requires.txt
pyopenapi.egg-info/top_level.txt
pyopenapi/migration/__init__.py
pyopenapi/migration/base.py
pyopenapi/migration/getter.py
pyopenapi/migration/resolve.py
pyopenapi/migration/scan.py
pyopenapi/migration/store.py
pyopenapi/migration/spec/__init__.py
pyopenapi/migration/spec/attr.py
pyopenapi/migration/spec/obj.py
pyopenapi/migration/versions/__init__.py
pyopenapi/migration/versions/comm.py
pyopenapi/migration/versions/v1_2/__init__.py
pyopenapi/migration/versions/v1_2/main.py
pyopenapi/migration/versions/v1_2/objects.py
pyopenapi/migration/versions/v1_2/scanner/__init__.py
pyopenapi/migration/versions/v1_2/scanner/upgrade.py
pyopenapi/migration/versions/v2_0/__init__.py
pyopenapi/migration/versions/v2_0/attrs.py
pyopenapi/migration/versions/v2_0/main.py
pyopenapi/migration/versions/v2_0/objects.py
pyopenapi/migration/versions/v2_0/scanner/__init__.py
pyopenapi/migration/versions/v2_0/scanner/merge.py
pyopenapi/migration/versions/v2_0/scanner/norm_ref.py
pyopenapi/migration/versions/v2_0/scanner/resolve.py
pyopenapi/migration/versions/v2_0/scanner/yaml.py
pyopenapi/migration/versions/v2_0/scanner/upgrade/__init__.py
pyopenapi/migration/versions/v2_0/scanner/upgrade/constants.py
pyopenapi/migration/versions/v2_0/scanner/upgrade/converters.py
pyopenapi/migration/versions/v2_0/scanner/upgrade/parameter_context.py
pyopenapi/migration/versions/v3_0_0/__init__.py
pyopenapi/migration/versions/v3_0_0/attrs.py
pyopenapi/migration/versions/v3_0_0/main.py
pyopenapi/migration/versions/v3_0_0/objects.py
pyopenapi/migration/versions/v3_0_0/scanner/__init__.py
pyopenapi/migration/versions/v3_0_0/scanner/merge.py
pyopenapi/migration/versions/v3_0_0/scanner/norm_ref.py
pyopenapi/migration/versions/v3_0_0/scanner/resolve.py