Metadata-Version: 1.1
Name: pyopenapi
Version: 0.0.1
Summary: Library for developing backward-compatible tools on OpenAPI
Home-page: https://github.com/pyopenapi/pyopenapi
Author: Mission Liao
Author-email: missionaryliao@gmail.com
License: UNKNOWN
Download-URL: https://github.com/pyopenapi/pyopenapi/tarball/0.0.1
Keywords: OepnAPI,REST
Platform: UNKNOWN
Classifier: Development Status :: 4 - Beta
Classifier: Intended Audience :: Developers
Classifier: License :: OSI Approved :: MIT License
Classifier: Operating System :: OS Independent
Classifier: Programming Language :: Python :: 2.6
Classifier: Programming Language :: Python :: 2.7
Classifier: Programming Language :: Python :: 3.3
Classifier: Programming Language :: Python :: 3.4
Classifier: Topic :: Software Development :: Libraries :: Python Modules
